src/dual_clock_fifo.v
module dual_clock_fifo (
    input wire clk1,          // Sampling clock
    input wire clk2,          // Core clock
    input wire reset,         // Asynchronous reset
    input wire [7:0] data_in, // 8-bit data input
    input wire write_en,      // Write enable
    input wire read_en,       // Read enable
    output reg [7:0] data_out,// 8-bit data output
    output reg full,          // FIFO full flag
    output reg empty          // FIFO empty flag
);

    // Parameters
    parameter FIFO_DEPTH = 16; // Adjust depth as needed
    parameter ADDR_WIDTH = 4;  // Address width (log2(FIFO_DEPTH))

    // Internal signals
    reg [7:0] fifo_mem [0:FIFO_DEPTH-1]; // FIFO memory
    reg [ADDR_WIDTH-1:0] write_ptr = 0;  // Write pointer
    reg [ADDR_WIDTH-1:0] read_ptr = 0;   // Read pointer
    reg [ADDR_WIDTH:0] count = 0;        // Count for tracking occupancy

    // Write operation (synchronized with clk1)
    always @(posedge clk1 or posedge reset) begin
        if (reset) begin
            write_ptr <= 0;
            full <= 0;
        end else if (write_en && !full) begin
            fifo_mem[write_ptr] <= data_in;
            write_ptr <= write_ptr + 1;
            if (write_ptr + 1 == read_ptr) full <= 1; // Check for full condition
            else full <= 0;
        end
    end

    // Read operation (synchronized with clk2)
    always @(posedge clk2 or posedge reset) begin
        if (reset) begin
            read_ptr <= 0;
            empty <= 1;
        end else if (read_en && !empty) begin
            data_out <= fifo_mem[read_ptr];
            read_ptr <= read_ptr + 1;
            if (read_ptr + 1 == write_ptr) empty <= 1; // Check for empty condition
            else empty <= 0;
        end
    end

    // Occupancy tracking
    always @(posedge clk1 or posedge clk2 or posedge reset) begin
        if (reset) count <= 0;
        else if (write_en && !full && !(read_en && !empty)) count <= count + 1;
        else if (read_en && !empty && !(write_en && !full)) count <= count - 1;
    end
endmodule

sim/dual_clock_fifo_tb.v
`timescale 1ns / 1ps

module dual_clock_fifo_tb;
    // Parameters
    localparam DATA_WIDTH = 8;
    localparam FIFO_DEPTH = 16;

    // Testbench signals
    reg clk1, clk2, reset;
    reg [DATA_WIDTH-1:0] data_in;
    reg write_en, read_en;
    wire [DATA_WIDTH-1:0] data_out;
    wire full, empty;

    // Instantiate the FIFO module
    dual_clock_fifo #(
        .DATA_WIDTH(DATA_WIDTH),
        .FIFO_DEPTH(FIFO_DEPTH)
    ) uut (
        .clk1(clk1),
        .clk2(clk2),
        .reset(reset),
        .data_in(data_in),
        .write_en(write_en),
        .read_en(read_en),
        .data_out(data_out),
        .full(full),
        .empty(empty)
    );

    // Clock generation
    always #50000 clk1 = ~clk1; // 10 kHz clock: Period = 100 µs = 50000 ns
    always #20000 clk2 = ~clk2; // Core clock: Period = 40 µs = 20000 ns (25 kHz)

    // Testbench procedure
    initial begin
        // Initialize signals
        clk1 = 0;
        clk2 = 0;
        reset = 1;
        write_en = 0;
        read_en = 0;
        data_in = 0;

        // Reset sequence
        #100000 reset = 0; // Release reset after 100 µs

        // Write data into the FIFO
        #100000 write_en = 1; data_in = 8'hAA; // Write 0xAA
        #100000 data_in = 8'h55;               // Write 0x55
        #100000 write_en = 0;                  // Stop writing

        // Read data from the FIFO
        #200000 read_en = 1;                   // Start reading
        #100000 read_en = 0;                   // Stop reading

        // End the simulation
        #500000 $finish;
    end

    // VCD file generation for waveform analysis
    initial begin
        $dumpfile("sim/dual_clock_fifo.vcd");
        $dumpvars(0, dual_clock_fifo_tb);
    end
endmodule

sim/dual_clock_fifo.vcd
$date
	Fri Nov  1 12:53:44 2024
$end
$version
	Icarus Verilog
$end
$timescale
	1ps
$end
$scope module dual_clock_fifo_tb $end
$var wire 1 ! full $end
$var wire 1 " empty $end
$var wire 8 # data_out [7:0] $end
$var reg 1 $ clk1 $end
$var reg 1 % clk2 $end
$var reg 8 & data_in [7:0] $end
$var reg 1 ' read_en $end
$var reg 1 ( reset $end
$var reg 1 ) write_en $end
$scope module uut $end
$var wire 1 $ clk1 $end
$var wire 1 % clk2 $end
$var wire 8 * data_in [7:0] $end
$var wire 1 ' read_en $end
$var wire 1 ( reset $end
$var wire 1 ) write_en $end
$var wire 1 ! full $end
$var wire 1 " empty $end
$var reg 5 + count [4:0] $end
$var reg 8 , data_out [7:0] $end
$var reg 4 - read_ptr [3:0] $end
$var reg 4 . write_ptr [3:0] $end
$upscope $end
$upscope $end
$enddefinitions $end
#0
$dumpvars
b0 .
b0 -
bx ,
b0 +
b0 *
0)
1(
0'
b0 &
0%
0$
bx #
1"
0!
$end
#20000000
1%
#40000000
0%
#50000000
1$
#60000000
1%
#80000000
0%
#100000000
1%
0$
0(
#120000000
0%
#140000000
1%
#150000000
1$
#160000000
0%
#180000000
1%
#200000000
0%
0$
b10101010 &
b10101010 *
1)
#220000000
0"
b1 +
1%
#240000000
0%
#250000000
b10 +
b1 .
1$
#260000000
b11 +
1%
#280000000
0%
#300000000
b100 +
1%
0$
b1010101 &
b1010101 *
#320000000
0%
#340000000
b101 +
1%
#350000000
b110 +
b10 .
1$
#360000000
0%
#380000000
b111 +
1%
#400000000
0%
0$
0)
#420000000
1%
#440000000
0%
#450000000
1$
#460000000
1%
#480000000
0%
#500000000
1%
0$
#520000000
0%
#540000000
1%
#550000000
1$
#560000000
0%
#580000000
1%
#600000000
0%
0$
1'
#620000000
b110 +
b1 -
b10101010 #
b10101010 ,
1%
#640000000
0%
#650000000
b101 +
1$
#660000000
b100 +
b10 -
b1010101 #
b1010101 ,
1%
#680000000
0%
#700000000
1%
0$
0'
