src/dual_clock_fifo.v
module dual_clock_fifo (
    input wire clk1,          // Sampling clock
    input wire clk2,          // Core clock
    input wire reset,         // Asynchronous reset
    input wire [7:0] data_in, // 8-bit data input
    input wire write_en,      // Write enable
    input wire read_en,       // Read enable
    output reg [7:0] data_out,// 8-bit data output
    output reg full,          // FIFO full flag
    output reg empty          // FIFO empty flag
);

    // Parameters
    parameter FIFO_DEPTH = 16; // Adjust depth as needed
    parameter ADDR_WIDTH = 4;  // Address width (log2(FIFO_DEPTH))

    // Internal signals
    reg [7:0] fifo_mem [0:FIFO_DEPTH-1]; // FIFO memory
    reg [ADDR_WIDTH-1:0] write_ptr = 0;  // Write pointer
    reg [ADDR_WIDTH-1:0] read_ptr = 0;   // Read pointer
    reg [ADDR_WIDTH:0] count = 0;        // Count for tracking occupancy

    // Write operation (synchronized with clk1)
    always @(posedge clk1 or posedge reset) begin
        if (reset) begin
            write_ptr <= 0;
            full <= 0;
        end else if (write_en && !full) begin
            fifo_mem[write_ptr] <= data_in;
            write_ptr <= write_ptr + 1;
            if (write_ptr + 1 == read_ptr) full <= 1; // Check for full condition
            else full <= 0;
        end
    end

    // Read operation (synchronized with clk2)
    always @(posedge clk2 or posedge reset) begin
        if (reset) begin
            read_ptr <= 0;
            empty <= 1;
        end else if (read_en && !empty) begin
            data_out <= fifo_mem[read_ptr];
            read_ptr <= read_ptr + 1;
            if (read_ptr + 1 == write_ptr) empty <= 1; // Check for empty condition
            else empty <= 0;
        end
    end

    // Occupancy tracking
    always @(posedge clk1 or posedge clk2 or posedge reset) begin
        if (reset) count <= 0;
        else if (write_en && !full && !(read_en && !empty)) count <= count + 1;
        else if (read_en && !empty && !(write_en && !full)) count <= count - 1;
    end
endmodule

sim/dual_clock_fifo_tb.v
`timescale 1ns / 1ps

module dual_clock_fifo_tb;
    // Clock and reset signals
    reg clk1, clk2, reset;
    reg [7:0] data_in;
    reg write_en, read_en;
    wire [7:0] data_out;
    wire full, empty;

    // Instantiate the FIFO module
    dual_clock_fifo uut (
        .clk1(clk1),
        .clk2(clk2),
        .reset(reset),
        .data_in(data_in),
        .write_en(write_en),
        .read_en(read_en),
        .data_out(data_out),
        .full(full),
        .empty(empty)
    );

    // Clock generation
    always #50 clk1 = ~clk1; // 10 kHz clock (100 ns period)
    always #30 clk2 = ~clk2; // Higher frequency clock (adjust as needed)

    // Test stimulus
    initial begin
        // Initialize signals
        clk1 = 0;
        clk2 = 0;
        reset = 1;
        write_en = 0;
        read_en = 0;
        data_in = 8'b0;

        // Reset sequence
        #100 reset = 0;

        // Write some data into FIFO
        #100 write_en = 1; data_in = 8'b10101010;
        #100 write_en = 0;

        // Read data from FIFO
        #200 read_en = 1;
        #100 read_en = 0;

        // End simulation
        #500 $finish;
    end

    // Dump waveforms
    initial begin
        $dumpfile("sim/dual_clock_fifo.vcd");
        $dumpvars(0, dual_clock_fifo_tb);
    end
endmodule

sim/dual_clock_fifo.vcd
$date
	Fri Nov  1 12:45:41 2024
$end
$version
	Icarus Verilog
$end
$timescale
	1ps
$end
$scope module dual_clock_fifo_tb $end
$var wire 1 ! full $end
$var wire 1 " empty $end
$var wire 8 # data_out [7:0] $end
$var reg 1 $ clk1 $end
$var reg 1 % clk2 $end
$var reg 8 & data_in [7:0] $end
$var reg 1 ' read_en $end
$var reg 1 ( reset $end
$var reg 1 ) write_en $end
$scope module uut $end
$var wire 1 $ clk1 $end
$var wire 1 % clk2 $end
$var wire 8 * data_in [7:0] $end
$var wire 1 ' read_en $end
$var wire 1 ( reset $end
$var wire 1 ) write_en $end
$var reg 5 + count [4:0] $end
$var reg 8 , data_out [7:0] $end
$var reg 1 " empty $end
$var reg 1 ! full $end
$var reg 4 - read_ptr [3:0] $end
$var reg 4 . write_ptr [3:0] $end
$upscope $end
$upscope $end
$enddefinitions $end
#0
$dumpvars
b0 .
b0 -
bx ,
b0 +
b0 *
0)
1(
0'
b0 &
0%
0$
bx #
1"
0!
$end
#30000
1%
#50000
1$
#60000
0%
#90000
1%
#100000
0$
0(
#120000
0%
#150000
1%
1$
#180000
0%
#200000
0$
b10101010 &
b10101010 *
1)
#210000
b1 +
1%
#240000
0%
#250000
b10 +
b1 .
1$
#270000
b11 +
1%
#300000
0%
0$
0)
#330000
1%
#350000
1$
#360000
0%
#390000
1%
#400000
0$
#420000
0%
#450000
1%
1$
#480000
0%
#500000
0$
1'
#510000
1%
#540000
0%
#550000
1$
#570000
1%
#600000
0%
0$
0'
